schedule_manager/__init__.py
schedule_manager/exceptions.py
schedule_manager/manager.py
schedule_manager-0.1.1.dist-info/LICENSE
schedule_manager-0.1.1.dist-info/METADATA
schedule_manager-0.1.1.dist-info/WHEEL
schedule_manager-0.1.1.dist-info/top_level.txt
schedule_manager-0.1.1.dist-info/RECORD
