Metadata-Version: 2.1
Name: schedule-manager
Version: 0.1.1
Summary: Thread-based task scheduling management.
Home-page: https://github.com/e619003/ScheduleManager
Author: James Chiang
Author-email: e619003@gmail.com
License: MIT
Keywords: schedule,periodic,jobs,daily,weekly,monthly,scheduling,scheduling management,scheduling manager,scheduler
Platform: UNKNOWN
Classifier: License :: OSI Approved :: MIT License
Classifier: Programming Language :: Python
Classifier: Intended Audience :: Developers
